latentforce_extractors/__init__.py
latentforce_extractors/config.py
latentforce_extractors/extractors.py
latentforce_extractors-2.0.dist-info/LICENSE
latentforce_extractors-2.0.dist-info/METADATA
latentforce_extractors-2.0.dist-info/WHEEL
latentforce_extractors-2.0.dist-info/top_level.txt
latentforce_extractors-2.0.dist-info/RECORD
