Metadata-Version: 2.1
Name: latentforce-extractors
Version: 2.0
Summary: Python client for Extractors.ai
Author-email: Aravind Jayendran <aravind@latantforce.ai>
License:                                  Apache License
Requires-Python: >=3.8
License-File: LICENSE
Requires-Dist: requests
Requires-Dist: openai
